README.md
setup.cfg
setup.py
pyopereto/__init__.py
pyopereto/client.py
pyopereto/command_line.py
pyopereto/diagnostics.py
pyopereto.egg-info/PKG-INFO
pyopereto.egg-info/SOURCES.txt
pyopereto.egg-info/dependency_links.txt
pyopereto.egg-info/entry_points.txt
pyopereto.egg-info/requires.txt
pyopereto.egg-info/top_level.txt
pyopereto/helpers/__init__.py
pyopereto/helpers/processes.py
pyopereto/tests/__init__.py
pyopereto/tests/conftest.py
pyopereto/tests/test_benchmark.py
pyopereto/tests/microservices/__init__.py
pyopereto/tests/microservices/opereto_test_service/__init__.py
pyopereto/tests/microservices/opereto_test_service/run.py
pyopereto/tests/microservices/opereto_test_service/service.md
pyopereto/tests/microservices/opereto_test_service/service.sam.json
pyopereto/tests/microservices/opereto_test_service/service.yaml