Metadata-Version: 1.1
Name: pyopereto
Version: 1.0.151
Summary: Opereto Python Client
Home-page: https://github.com/opereto/pyopereto
Author: Dror Russo
Author-email: dror.russo@opereto.com
License: UNKNOWN
Download-URL: https://github.com/opereto/pyopereto/archive/1.0.151.tar.gz
Platform: UNKNOWN
